ctyunsdk_vpn20220909/__init__.py
ctyunsdk_vpn20220909/vpn_client.py
ctyunsdk_vpn20220909/models/__init__.py
ctyunsdk_vpn20220909/models/ipsec_vpn_static_route_create.py
ctyunsdk_vpn20220909/models/v4_vpn_gateway_query_price_new.py
ctyunsdk_vpn20220909/models/v4_vpn_gateway_query_price_renew.py
ctyunsdk_vpn20220909/models/v4_vpn_gateway_query_price_upgrade.py
ctyunsdk_vpn20220909/models/v4_vpn_ipsec_health_check_create.py
ctyunsdk_vpn20220909/models/v4_vpn_ipsec_health_check_list.py
ctyunsdk_vpn20220909/models/v4_vpn_ipsec_policy_route_list.py
ctyunsdk_vpn20220909/models/v4_vpn_ipsec_qos_limit_delete.py
ctyunsdk_vpn20220909/models/v4_vpn_ipsec_qos_limit_list.py
ctyunsdk_vpn20220909/models/v4_vpn_ipsec_qos_limit_update.py
ctyunsdk_vpn20220909/models/v4_vpn_ipsec_static_route_list.py
ctyunsdk_vpn20220909/models/v4_vpn_ipsec_user_service_list.py
ctyunsdk_vpn20220909/models/v4_vpn_ipsec_user_service_update.py
ctyunsdk_vpn20220909/models/v4_vpn_ipsec_vpn_connection_create.py
ctyunsdk_vpn20220909/models/v4_vpn_ipsec_vpn_connection_delete.py
ctyunsdk_vpn20220909/models/v4_vpn_ipsec_vpn_connection_list.py
ctyunsdk_vpn20220909/models/v4_vpn_ipsec_vpn_connection_log_list.py
ctyunsdk_vpn20220909/models/v4_vpn_ipsec_vpn_connection_policy_detail_list.py
ctyunsdk_vpn20220909/models/v4_vpn_ipsec_vpn_connection_update.py
ctyunsdk_vpn20220909/models/v4_vpn_ssl_client_create.py
ctyunsdk_vpn20220909/models/v4_vpn_ssl_client_delete.py
ctyunsdk_vpn20220909/models/v4_vpn_ssl_client_disconnect.py
ctyunsdk_vpn20220909/models/v4_vpn_ssl_client_get_secret.py
ctyunsdk_vpn20220909/models/v4_vpn_ssl_client_keyword_update.py
ctyunsdk_vpn20220909/models/v4_vpn_ssl_client_list.py
ctyunsdk_vpn20220909/models/v4_vpn_ssl_client_qos_update.py
ctyunsdk_vpn20220909/models/v4_vpn_ssl_client_reset_keyword.py
ctyunsdk_vpn20220909/models/v4_vpn_ssl_client_update.py
ctyunsdk_vpn20220909/models/v4_vpn_ssl_server_create.py
ctyunsdk_vpn20220909/models/v4_vpn_ssl_server_delete.py
ctyunsdk_vpn20220909-2.0.1.dist-info/licenses/LICENSE.txt
ctyunsdk_vpn20220909-2.0.1.dist-info/METADATA
ctyunsdk_vpn20220909-2.0.1.dist-info/WHEEL
ctyunsdk_vpn20220909-2.0.1.dist-info/top_level.txt
ctyunsdk_vpn20220909-2.0.1.dist-info/RECORD
